scvf/__init__.py
scvf/constants.py
scvf/cv_loop.py
scvf/io/__init__.py
scvf/io/nt_io.py
scvf/loops/__init__.py
scvf/loops/camera_loop.py
scvf/loops/pipeline_loop.py
scvf/loops/settings_callback.py
scvf/util/__init__.py
scvf/util/camera_manager.py
scvf/util/image_container.py
scvf/util/pipeline_manager.py
scvf/util/settings.py
scvf-1.0.2.dist-info/METADATA
scvf-1.0.2.dist-info/RECORD
scvf-1.0.2.dist-info/WHEEL
scvf-1.0.2.dist-info/top_level.txt
