Metadata-Version: 2.1
Name: scvf
Version: 1.0.2
Summary: a framework that wraps opencv for our needs in FRC
Home-page: https://github.com/Spikes-2212-Programming-Guild/SpikesCVFramework
Author: Spikes#2212
Author-email: spikesno2212@gmail.com
License: UNKNOWN
Platform: UNKNOWN
Classifier: Programming Language :: Python :: 3
Classifier: License :: OSI Approved :: MIT License
Classifier: Operating System :: OS Independent
